hebo/__init__.py
hebo/sklearn_tuner.py
hebo/acq_optimizers/__init__.py
hebo/acq_optimizers/evolution_optimizer.py
hebo/acquisitions/__init__.py
hebo/acquisitions/acq.py
hebo/benchmarks/__init__.py
hebo/benchmarks/synthetic_benchmarks.py
hebo/design_space/__init__.py
hebo/design_space/bool_param.py
hebo/design_space/categorical_param.py
hebo/design_space/design_space.py
hebo/design_space/int_exponent_param.py
hebo/design_space/integer_param.py
hebo/design_space/numeric_param.py
hebo/design_space/param.py
hebo/design_space/pow_integer_param.py
hebo/design_space/pow_param.py
hebo/design_space/step_int.py
hebo/models/__init__.py
hebo/models/base_model.py
hebo/models/layers.py
hebo/models/model_factory.py
hebo/models/scalers.py
hebo/models/util.py
hebo/models/boosting/__init__.py
hebo/models/boosting/catboost.py
hebo/models/gp/__init__.py
hebo/models/gp/gp.py
hebo/models/gp/gp_util.py
hebo/models/gp/gpy_mlp.py
hebo/models/gp/gpy_wgp.py
hebo/models/gp/svgp.py
hebo/models/gp/svidkl.py
hebo/models/nn/__init__.py
hebo/models/nn/conditional_deep_ensemble.py
hebo/models/nn/deep_ensemble.py
hebo/models/nn/fe_deep_ensemble.py
hebo/models/nn/fe_layers.py
hebo/models/nn/gumbel_linear.py
hebo/models/nn/mcbn.py
hebo/models/nn/sgld.py
hebo/models/nn/eac/__init__.py
hebo/models/nn/eac/eac_ensemble.py
hebo/models/nn/eac/eac_model.py
hebo/models/nn/eac/embedding_alignment_cell.py
hebo/models/nn/eac/masked_deep_ensemble.py
hebo/models/nn/eac/positional_encoding.py
hebo/models/rf/__init__.py
hebo/models/rf/rf.py
hebo/optimizers/__init__.py
hebo/optimizers/abstract_optimizer.py
hebo/optimizers/bo.py
hebo/optimizers/cmaes.py
hebo/optimizers/evolution.py
hebo/optimizers/general.py
hebo/optimizers/hebo.py
hebo/optimizers/hebo_contextual.py
hebo/optimizers/hebo_embedding.py
hebo/optimizers/noisy_opt.py
hebo/optimizers/nomr.py
hebo/optimizers/util.py
test/__init__.py
test/test_acq.py
test/test_base_model.py
test/test_categorical_encoder.py
test/test_concrete.py
HEBO-0.3.6.dist-info/LICENSE
HEBO-0.3.6.dist-info/METADATA
HEBO-0.3.6.dist-info/WHEEL
HEBO-0.3.6.dist-info/top_level.txt
HEBO-0.3.6.dist-info/RECORD
