Metadata-Version: 2.1
Name: HEBO
Version: 0.3.6
Summary: Heteroscedastic evolutionary bayesian optimisation
Home-page: https://github.com/huawei-noah/HEBO/tree/master/HEBO
Classifier: License :: OSI Approved :: MIT License
License-File: LICENSE
Requires-Dist: numpy <1.25,>=1.16
Requires-Dist: pandas >=1.0.1
Requires-Dist: torch >=1.9.0
Requires-Dist: pymoo ==0.6.0
Requires-Dist: scikit-learn >=0.22
Requires-Dist: gpytorch >=1.4.0
Requires-Dist: GPy >=1.9.9
Requires-Dist: catboost >=0.24.4
Requires-Dist: disjoint-set
